pdbdownload/__init__.py
pdbdownload/__main__.py
pdbdownload-1.3.dist-info/METADATA
pdbdownload-1.3.dist-info/WHEEL
pdbdownload-1.3.dist-info/entry_points.txt
pdbdownload-1.3.dist-info/top_level.txt
pdbdownload-1.3.dist-info/RECORD
